alumathgroup13/__init__.py
alumathgroup13/matrix_operations.py
group13_matrix_operations_2025-1.0.0.dist-info/licenses/LICENSE
group13_matrix_operations_2025-1.0.0.dist-info/METADATA
group13_matrix_operations_2025-1.0.0.dist-info/WHEEL
group13_matrix_operations_2025-1.0.0.dist-info/top_level.txt
group13_matrix_operations_2025-1.0.0.dist-info/RECORD
